{"is_source_file": true, "format": "JavaScript", "description": "This file defines a React context and provider for managing a list of todos, including state management with useReducer, side effects with useEffect, and API interactions for CRUD operations.", "external_files": ["../utils/api"], "external_methods": ["listTodos", "createTodo", "updateTodo", "deleteTodo"], "published": ["TodoProvider", "useTodos"], "classes": [], "methods": [{"name": "reducer(state, action)", "description": "Handles state transitions based on dispatched action types for todo list management.", "scope": "", "scopeKind": ""}, {"name": "TodoProvider({ children })", "description": "React component providing the todo state and actions via context to its children.", "scope": "", "scopeKind": ""}, {"name": "useTodos()", "description": "Custom React hook to access the todo state and actions from context.", "scope": "", "scopeKind": ""}], "calls": ["listTodos", "createTodo", "updateTodo", "deleteTodo", "useReducer", "useContext", "useEffect", "useCallback"], "search-terms": ["TodoContext", "useReducer for todos", "React context for todos", "Load todos asynchronously", "Todo API interactions", "Todo state management"], "state": 2, "file_id": 14, "knowledge_revision": 29, "git_revision": "", "ctags": [{"_type": "tag", "name": "TodoDispatchContext", "path": "/home/kavia/workspace/code-generation/task-management-web-app-225782-225791/todo_frontend/src/context/TodoContext.js", "pattern": "/^const TodoDispatchContext = createContext();$/", "language": "JavaScript", "kind": "constant"}, {"_type": "tag", "name": "TodoProvider", "path": "/home/kavia/workspace/code-generation/task-management-web-app-225782-225791/todo_frontend/src/context/TodoContext.js", "pattern": "/^export function TodoProvider({ children }) {$/", "language": "JavaScript", "kind": "function", "signature": "({ children })"}, {"_type": "tag", "name": "TodoStateContext", "path": "/home/kavia/workspace/code-generation/task-management-web-app-225782-225791/todo_frontend/src/context/TodoContext.js", "pattern": "/^const TodoStateContext = createContext();$/", "language": "JavaScript", "kind": "constant"}, {"_type": "tag", "name": "error", "path": "/home/kavia/workspace/code-generation/task-management-web-app-225782-225791/todo_frontend/src/context/TodoContext.js", "pattern": "/^  error: null,$/", "language": "JavaScript", "kind": "property", "scope": "initialState", "scopeKind": "class"}, {"_type": "tag", "name": "initialState", "path": "/home/kavia/workspace/code-generation/task-management-web-app-225782-225791/todo_frontend/src/context/TodoContext.js", "pattern": "/^const initialState = {$/", "language": "JavaScript", "kind": "class"}, {"_type": "tag", "name": "loading", "path": "/home/kavia/workspace/code-generation/task-management-web-app-225782-225791/todo_frontend/src/context/TodoContext.js", "pattern": "/^  loading: false,$/", "language": "JavaScript", "kind": "property", "scope": "initialState", "scopeKind": "class"}, {"_type": "tag", "name": "reducer", "path": "/home/kavia/workspace/code-generation/task-management-web-app-225782-225791/todo_frontend/src/context/TodoContext.js", "pattern": "/^function reducer(state, action) {$/", "language": "JavaScript", "kind": "function", "signature": "(state, action)"}, {"_type": "tag", "name": "todos", "path": "/home/kavia/workspace/code-generation/task-management-web-app-225782-225791/todo_frontend/src/context/TodoContext.js", "pattern": "/^  todos: [],$/", "language": "JavaScript", "kind": "property", "scope": "initialState", "scopeKind": "class"}, {"_type": "tag", "name": "useTodos", "path": "/home/kavia/workspace/code-generation/task-management-web-app-225782-225791/todo_frontend/src/context/TodoContext.js", "pattern": "/^export function useTodos() {$/", "language": "JavaScript", "kind": "function", "signature": "()"}, {"_type": "tag", "name": "value", "path": "/home/kavia/workspace/code-generation/task-management-web-app-225782-225791/todo_frontend/src/context/TodoContext.js", "pattern": "/^    <TodoStateContext.Provider value={value}>$/", "language": "JavaScript", "kind": "field", "scope": "Provider", "scopeKind": "class"}], "hash": "ff3b3415b5e4f0c29788acf7bccae9fa", "format-version": 4, "code-base-name": "todo_frontend", "filename": "todo_frontend/src/context/TodoContext.js", "fields": [{"name": "error: null,", "scope": "initialState", "scopeKind": "class", "description": "unavailable"}, {"name": "loading: false,", "scope": "initialState", "scopeKind": "class", "description": "unavailable"}, {"name": "todos: [],", "scope": "initialState", "scopeKind": "class", "description": "unavailable"}, {"name": "<TodoStateContext.Provider value={value}>", "scope": "Provider", "scopeKind": "class", "description": "unavailable"}], "revision_history": [{"29": ""}]}